logdna_line_export/__init__.py
logdna_line_export/main.py
logdna_line_export-0.0.2.dist-info/METADATA
logdna_line_export-0.0.2.dist-info/WHEEL
logdna_line_export-0.0.2.dist-info/entry_points.txt
logdna_line_export-0.0.2.dist-info/top_level.txt
logdna_line_export-0.0.2.dist-info/RECORD
